{
  "IsEncrypted": false,
  "Values": {
    "AzureWebJobsStorage": "UseDevelopmentStorage=true",
    "FUNCTIONS_WORKER_RUNTIME": "dotnet-isolated",
    "AzureWebJobsServiceBus": "Endpoint=sb://dummy.servicebus.windows.net/;SharedAccessKeyName=dummy;SharedAccessKey=dummy",
    "NServiceBus_License": "",
    "ConfigNames": "SFA.DAS.EmployerFinance.Jobs.V2",
    "FinanceApiConfiguration:Url": "http://localhost:5001",
    "FinanceApiConfiguration:Identifier": "",
    "ProviderPaymentApiConfiguration:Url": "http://localhost:5001",
    "ProviderPaymentApiConfiguration:Identifier": ""
  }
}